kuzualchemy/BaseModel.py
kuzualchemy/__init__.py
kuzualchemy/connection_pool.py
kuzualchemy/constants.py
kuzualchemy/kuzu_function_types.py
kuzualchemy/kuzu_functions.py
kuzualchemy/kuzu_orm.py
kuzualchemy/kuzu_query.py
kuzualchemy/kuzu_query_builder.py
kuzualchemy/kuzu_query_expressions.py
kuzualchemy/kuzu_query_fields.py
kuzualchemy/kuzu_session.py
kuzualchemy/test_utilities.py
kuzualchemy-0.2.0.dist-info/licenses/LICENSE
kuzualchemy-0.2.0.dist-info/METADATA
kuzualchemy-0.2.0.dist-info/WHEEL
kuzualchemy-0.2.0.dist-info/top_level.txt
kuzualchemy-0.2.0.dist-info/RECORD
