Metadata-Version: 2.4
Name: kuzualchemy
Version: 0.2.0
Summary: SQLAlchemy-like ORM for Kuzu graph database
Author-email: FanaticPythoner <info@kuzualchemy.com>
License: GPL-3.0
Project-URL: Homepage, https://github.com/FanaticPythoner/kuzualchemy
Project-URL: Documentation, https://kuzualchemy.readthedocs.io
Project-URL: Repository, https://github.com/FanaticPythoner/kuzualchemy
Project-URL: Bug Tracker, https://github.com/FanaticPythoner/kuzualchemy/issues
Keywords: kuzu,graph,database,orm,sqlalchemy,cypher,graph-database
Classifier: Development Status :: 4 - Beta
Classifier: Intended Audience :: Developers
Classifier: Operating System :: OS Independent
Classifier: Programming Language :: Python :: 3
Classifier: Programming Language :: Python :: 3.8
Classifier: Programming Language :: Python :: 3.9
Classifier: Programming Language :: Python :: 3.10
Classifier: Programming Language :: Python :: 3.11
Classifier: Programming Language :: Python :: 3.12
Classifier: Topic :: Database
Classifier: Topic :: Database :: Database Engines/Servers
Classifier: Topic :: Software Development :: Libraries :: Python Modules
Classifier: Typing :: Typed
Requires-Python: >=3.8
License-File: LICENSE
Requires-Dist: pydantic>=2.0.0
Requires-Dist: kuzu
Requires-Dist: typing-extensions
Requires-Dist: polars
Requires-Dist: pyarrow
Requires-Dist: pyahocorasick
Requires-Dist: importlib-metadata>=1.0; python_version < "3.8"
Provides-Extra: dev
Requires-Dist: pytest>=7.0.0; extra == "dev"
Requires-Dist: pytest-asyncio>=0.21.0; extra == "dev"
Requires-Dist: pytest-cov>=4.0.0; extra == "dev"
Requires-Dist: pytest-mock>=3.10.0; extra == "dev"
Requires-Dist: black>=23.0.0; extra == "dev"
Requires-Dist: isort>=5.12.0; extra == "dev"
Requires-Dist: mypy>=1.0.0; extra == "dev"
Requires-Dist: flake8>=6.0.0; extra == "dev"
Requires-Dist: pre-commit>=3.0.0; extra == "dev"
Provides-Extra: docs
Requires-Dist: sphinx>=6.0.0; extra == "docs"
Requires-Dist: sphinx-rtd-theme>=1.2.0; extra == "docs"
Requires-Dist: myst-parser>=1.0.0; extra == "docs"
Provides-Extra: test
Requires-Dist: pytest>=7.0.0; extra == "test"
Requires-Dist: pytest-asyncio>=0.21.0; extra == "test"
Requires-Dist: pytest-cov>=4.0.0; extra == "test"
Requires-Dist: pytest-mock>=3.10.0; extra == "test"
Requires-Dist: pytest-benchmark>=4.0.0; extra == "test"
Dynamic: license-file
